Php2pythonApiCankao2017925/README.md
Php2pythonApiCankao2017925/__init__.py
Php2pythonApiCankao2017925/__main__.py
Php2pythonApiCankao2017925/file.epub
Php2pythonApiCankao2017925/index.html
Php2pythonApiCankao2017925/css/__init__.py
Php2pythonApiCankao2017925/css/annotations.css
Php2pythonApiCankao2017925/css/main.css
Php2pythonApiCankao2017925/css/normalize.css
Php2pythonApiCankao2017925/css/popup.css
Php2pythonApiCankao2017925/font/__init__.py
Php2pythonApiCankao2017925/font/fontello.eot
Php2pythonApiCankao2017925/font/fontello.svg
Php2pythonApiCankao2017925/font/fontello.ttf
Php2pythonApiCankao2017925/font/fontello.woff
Php2pythonApiCankao2017925/img/__init__.py
Php2pythonApiCankao2017925/img/annotator-glyph-sprite.png
Php2pythonApiCankao2017925/img/annotator-icon-sprite.png
Php2pythonApiCankao2017925/img/apple-touch-icon.png
Php2pythonApiCankao2017925/img/cancelfullscreen.png
Php2pythonApiCankao2017925/img/close.png
Php2pythonApiCankao2017925/img/fullscreen.png
Php2pythonApiCankao2017925/img/loader.gif
Php2pythonApiCankao2017925/img/menu-icon.png
Php2pythonApiCankao2017925/img/save.png
Php2pythonApiCankao2017925/img/saved.png
Php2pythonApiCankao2017925/img/settings-s.png
Php2pythonApiCankao2017925/img/settings.png
Php2pythonApiCankao2017925/img/star.png
Php2pythonApiCankao2017925/js/__init__.py
Php2pythonApiCankao2017925/js/epub.js
Php2pythonApiCankao2017925/js/epub.min.js
Php2pythonApiCankao2017925/js/epub.min.map
Php2pythonApiCankao2017925/js/hooks.min.js
Php2pythonApiCankao2017925/js/hooks.min.map
Php2pythonApiCankao2017925/js/reader.js
Php2pythonApiCankao2017925/js/reader.js.map
Php2pythonApiCankao2017925/js/reader.min.js
Php2pythonApiCankao2017925/js/reader.min.map
Php2pythonApiCankao2017925/js/hooks/__init__.py
Php2pythonApiCankao2017925/js/hooks/extensions/__init__.py
Php2pythonApiCankao2017925/js/hooks/extensions/highlight.js
Php2pythonApiCankao2017925/js/libs/__init__.py
Php2pythonApiCankao2017925/js/libs/jquery.min.js
php2python_api_cankao_2017_9_25-2024.3.2.0.dist-info/METADATA
php2python_api_cankao_2017_9_25-2024.3.2.0.dist-info/WHEEL
php2python_api_cankao_2017_9_25-2024.3.2.0.dist-info/entry_points.txt
php2python_api_cankao_2017_9_25-2024.3.2.0.dist-info/top_level.txt
php2python_api_cankao_2017_9_25-2024.3.2.0.dist-info/RECORD
